Y_lw/__init__.py
Y_lw/yellow.py
y_lw-0.2.2.dist-info/licenses/LICENSE
y_lw-0.2.2.dist-info/METADATA
y_lw-0.2.2.dist-info/WHEEL
y_lw-0.2.2.dist-info/top_level.txt
y_lw-0.2.2.dist-info/RECORD
