Metadata-Version: 2.4
Name: Y_lw
Version: 0.2.2
Summary: A simple library that prints a greeting.
Home-page: https://github.com/im-yellow/Y_ellow/
Author: Y-ellow
Author-email: im.yellow.dev@gmail.com
Classifier: Programming Language :: Python :: 3
Classifier: License :: OSI Approved :: MIT License
Classifier: Operating System :: OS Independent
Requires-Python: >=3.6
License-File: LICENSE
Dynamic: author
Dynamic: author-email
Dynamic: classifier
Dynamic: description
Dynamic: description-content-type
Dynamic: home-page
Dynamic: license-file
Dynamic: requires-python
Dynamic: summary
